hhai_tlbx/config_utils/Argparser.py
hhai_tlbx/config_utils/Configer.py
hhai_tlbx/config_utils/IO_Converter.py
hhai_tlbx/config_utils/__init__.py
hhai_tlbx/config_utils/utils/Flag.py
hhai_tlbx/config_utils/utils/Type_Convertor.py
hhai_tlbx/data_utils/__init__.py
hhai_tlbx/data_utils/ds_hub.py
hhai_tlbx/data_utils/ds_utils.py
hhai_tlbx-0.1.0.dist-info/METADATA
hhai_tlbx-0.1.0.dist-info/WHEEL
hhai_tlbx-0.1.0.dist-info/top_level.txt
hhai_tlbx-0.1.0.dist-info/RECORD
