Metadata-Version: 2.1
Name: hhai-tlbx
Version: 0.1.0
Summary: AI toolbox for Hon Hai research institution. Although, the primary utility only provide program configuration and data path preparation, more features will come out later
Home-page: https://github.com/HuangChiEn/hhai-tlbx
Author: JosefHuang
Author-email: a3285556aa@gmail.com
License: MIT
Keywords: configuration,commendline argument,argument
Classifier: Programming Language :: Python :: 3.6
Classifier: Programming Language :: Python :: 3.7
Classifier: Programming Language :: Python :: 3.8
Classifier: Programming Language :: Python :: 3.9
Requires-Python: >=3.6
